denario/__init__.py
denario/cli.py
denario/config.py
denario/denario.py
denario/experiment.py
denario/idea.py
denario/key_manager.py
denario/llm.py
denario/method.py
denario/research.py
denario/utils.py
denario/langgraph_agents/__init__.py
denario/langgraph_agents/agents_graph.py
denario/langgraph_agents/idea.py
denario/langgraph_agents/literature.py
denario/langgraph_agents/methods.py
denario/langgraph_agents/parameters.py
denario/langgraph_agents/pdf_reader.py
denario/langgraph_agents/prompts.py
denario/langgraph_agents/reader.py
denario/langgraph_agents/referee.py
denario/langgraph_agents/routers.py
denario/paper_agents/__init__.py
denario/paper_agents/agents_graph.py
denario/paper_agents/journal.py
denario/paper_agents/latex.py
denario/paper_agents/latex_presets.py
denario/paper_agents/literature.py
denario/paper_agents/paper_node.py
denario/paper_agents/parameters.py
denario/paper_agents/prompts.py
denario/paper_agents/reader.py
denario/paper_agents/routers.py
denario/paper_agents/tools.py
denario/paper_agents/LaTeX/AAS_keywords.txt
denario/paper_agents/LaTeX/JHEP.bst
denario/paper_agents/LaTeX/aas_macros.sty
denario/paper_agents/LaTeX/aasjournal.bst
denario/paper_agents/LaTeX/aastex631.cls
denario/paper_agents/LaTeX/fancyhdr.sty
denario/paper_agents/LaTeX/icml2025.bst
denario/paper_agents/LaTeX/icml2025.sty
denario/paper_agents/LaTeX/jcappub.sty
denario/paper_agents/LaTeX/neurips_2025.sty
denario/paper_agents/LaTeX/pasj01.cls
denario/prompts/experiment.py
denario/prompts/idea.py
denario/prompts/method.py
denario-1.0.1.dist-info/METADATA
denario-1.0.1.dist-info/WHEEL
denario-1.0.1.dist-info/entry_points.txt
denario-1.0.1.dist-info/licenses/LICENSE
denario-1.0.1.dist-info/RECORD
