Metadata-Version: 2.4
Name: denario
Version: 1.0.1
Summary: Modular Multi-Agent System for Scientific Research Assistance
Project-URL: Homepage, https://astropilot-ai.github.io/DenarioPaperPage/
Project-URL: Documentation, https://denario.readthedocs.io/en/latest/
Project-URL: Repository, https://github.com/AstroPilot-AI/Denario
Author: Pablo Villanueva-Domingo, Francisco Villaescusa-Navarro, Boris Bolliet
Maintainer-email: Denario <denario.astropilot.ai@gmail.com>
License: GPLv3
License-File: LICENSE
Keywords: agent,biology,chemistry,cosmology,llm,machine learning,material sciences
Requires-Python: <3.14,>=3.12
Requires-Dist: cmbagent>=0.0.1post63
Requires-Dist: filelock>=3.17.0
Requires-Dist: flatbuffers>=24.12.23
Requires-Dist: futurehouse-client
Requires-Dist: google-ai-generativelanguage>=0.6.17
Requires-Dist: google-cloud-aiplatform
Requires-Dist: json5
Requires-Dist: jsonschema
Requires-Dist: langchain-anthropic>=0.3.10
Requires-Dist: langchain-google-genai
Requires-Dist: langchain-openai>=0.3.12
Requires-Dist: langgraph>=0.3.25
Requires-Dist: pillow
Requires-Dist: pip
Requires-Dist: pymupdf
Provides-Extra: app
Requires-Dist: denario-app>=1.0.0; extra == 'app'
Provides-Extra: docs
Requires-Dist: mkdocs; extra == 'docs'
Requires-Dist: mkdocs-git-committers-plugin-2>=2.5.0; extra == 'docs'
Requires-Dist: mkdocs-jupyter>=0.25.1; extra == 'docs'
Requires-Dist: mkdocs-material>=9.6.12; extra == 'docs'
Requires-Dist: mkdocstrings[python]; extra == 'docs'
